ccnb/MigrationNetworkLatticeSites.py
ccnb/__init__.py
ccnb/bvse_cavd.py
ccnb/cavd_channel.py
ccnb/main.py
ccnb/mergecluster.py
ccnb/neb_packages.py
ccnb/path_poscar.py
ccnb/vasp_inputs.py
ccnb/vasp_parse.py
ccnb/zip_paths.py
ccnb/bvse/BVAnalysis.py
ccnb/bvse/BVSEParam.dat
ccnb/bvse/Structure.py
ccnb/bvse/__init__.py
ccnb/bvse/bvmparam.dat
ccnb/bvse/bvse.dat
ccnb/bvse/elements.dat
ccnb-0.2.3.dist-info/METADATA
ccnb-0.2.3.dist-info/WHEEL
ccnb-0.2.3.dist-info/entry_points.txt
ccnb-0.2.3.dist-info/top_level.txt
ccnb-0.2.3.dist-info/RECORD
