Metadata-Version: 2.1
Name: ccnb
Version: 0.2.3
Summary: UNKNOWN
Home-page: https://gitee.com/shuhebing/CCNB
Author: He Bing
Author-email: bhe@t.shu.edu.cn
License: UNKNOWN
Platform: UNKNOWN
Requires-Python: >=3.7,<3.10
Requires-Dist: ase (==3.15.0)
Requires-Dist: pymatgen (==2022.0.10)
Requires-Dist: cavd (==0.5.4)
Requires-Dist: networkx (==2.2)
